socialpretext/__init__.py
socialpretext/pipeline.py
socialpretext/_data/__init__.py
socialpretext/_data/contractions.py
socialpretext/_data/slang.py
socialpretext-0.1.0.dist-info/METADATA
socialpretext-0.1.0.dist-info/WHEEL
socialpretext-0.1.0.dist-info/top_level.txt
socialpretext-0.1.0.dist-info/RECORD
