Metadata-Version: 2.4
Name: socialpretext
Version: 0.1.0
Summary: A lightweight utility for preprocessing and cleaning social media text (slang, emojis, hashtags, etc.).
Author-email: Akash Goyal <akashpgoyal@gmail.com>
License: MIT
Project-URL: Homepage, https://github.com/akashgoyalll/socialpretext
Project-URL: Issues, https://github.com/akashgoyalll/socialpretext/issues
Keywords: nlp,text cleaning,preprocessing,slang,emoji,social media,socialpretext
Classifier: Programming Language :: Python :: 3
Classifier: License :: OSI Approved :: MIT License
Classifier: Operating System :: OS Independent
Classifier: Topic :: Text Processing :: Linguistic
Classifier: Intended Audience :: Developers
Classifier: Intended Audience :: Science/Research
Classifier: Natural Language :: English
Requires-Python: >=3.8
Requires-Dist: emoji>=2.0.0
